btcprompt/__init__.py
btcprompt/activate
btcprompt/run.py
btcprompt-0.0.1.dist-info/entry_points.txt
btcprompt-0.0.1.dist-info/LICENSE
btcprompt-0.0.1.dist-info/WHEEL
btcprompt-0.0.1.dist-info/METADATA
btcprompt-0.0.1.dist-info/RECORD
