Metadata-Version: 2.1
Name: btcprompt
Version: 0.0.1
Summary: show live BTC price in prompt line
Author-email: cryptothink <cryptothink629@gmail.com>
Classifier: License :: OSI Approved :: GNU General Public License v3 or later (GPLv3+)
Requires-Dist: beautifulsoup4
Project-URL: Home, https://github.com/cryptothink629
